{"pages_css_csssecret_index.md":"BYDVbQmf","pages_3d_index.md":"C7acCNXm","pages_vue_handrender.md":"CE7uGSFN","pages_vue_ast.md":"BQGgmtLX","pages_vue_index.md":"DGDMxyJE","pages_js_文档流.md":"VwiUDTXR","pages_datastructure_index.md":"DGgrvXIM","pages_js_函数重载.md":"m2799OTG","ways_index.md":"o8C346C6","pages_source_vite.md":"DX9vQfHC","pages_js_promise.md":"Cnd0b3jS","pages_enginee_index.md":"DgF4a3WO","pages_js_ao和vo.md":"CZzFNYIc","pages_dailyrecord_index.md":"CixgfVeG","pages_js_index.md":"J-aGchjB","pages_designpattern_index.md":"D02KIs9l","pages_dailyrecord_copy_index.md":"WXrTILgS","pages_css_css_index.md":"Bmxb_t7T","index.md":"CTrVD0dz","pages_interview_index.md":"BV0MZpUY","pages_css_tailwindcss_index.md":"Cg310VuS","pages_js_dom事件流.md":"pejx9Aum","pages_enginee_postcss_index.md":"Bs_sZkqX","pages_css_sass_index.md":"Cy7Whtj0"}
